[
  [
    {
      "target": "Temp",
      "X": [
        "19:00",
        "20:00",
        "21:00",
        "22:00",
        "23:00",
        "00:00",
        "01:00",
        "02:00",
        "03:00",
        "04:00",
        "05:00",
        "06:00",
        "07:00",
        "08:00",
        "09:00",
        "10:00",
        "11:00",
        "12:00",
        "13:00",
        "14:00",
        "15:00",
        "16:00",
        "17:00",
        "18:00"
      ],
      "y": [
        [
          20.23,
          19.56,
          19.41,
          15.66,
          16.32,
          15.19,
          14.55,
          15.0,
          15.7,
          14.98,
          15.76,
          15.65,
          16.14,
          16.23,
          17.1,
          17.01,
          17.8,
          17.53,
          17.13,
          18.11,
          17.86,
          17.83,
          16.7,
          17.57
        ]
      ],
      "mae": 0.4003
    },
    {
      "target": "Hum",
      "X": [
        "19:00",
        "20:00",
        "21:00",
        "22:00",
        "23:00",
        "00:00",
        "01:00",
        "02:00",
        "03:00",
        "04:00",
        "05:00",
        "06:00",
        "07:00",
        "08:00",
        "09:00",
        "10:00",
        "11:00",
        "12:00",
        "13:00",
        "14:00",
        "15:00",
        "16:00",
        "17:00",
        "18:00"
      ],
      "y": [
        [
          59.37,
          59.65,
          59.1,
          59.09,
          62.23,
          63.59,
          65.41,
          68.12,
          68.82,
          70.31,
          71.35,
          69.51,
          72.04,
          67.42,
          68.73,
          69.02,
          68.06,
          70.38,
          68.94,
          70.1,
          68.19,
          68.53,
          68.22,
          67.84
        ]
      ],
      "mae": 0.3827
    },
    {
      "target": "pres",
      "X": [
        "19:00",
        "20:00",
        "21:00",
        "22:00",
        "23:00",
        "00:00",
        "01:00",
        "02:00",
        "03:00",
        "04:00",
        "05:00",
        "06:00",
        "07:00",
        "08:00",
        "09:00",
        "10:00",
        "11:00",
        "12:00",
        "13:00",
        "14:00",
        "15:00",
        "16:00",
        "17:00",
        "18:00"
      ],
      "y": [
        [
          101490.4,
          101608.74,
          101581.25,
          101917.22,
          101964.25,
          101895.66,
          101949.05,
          101890.64,
          101844.85,
          101767.79,
          101668.0,
          101700.44,
          101659.89,
          101548.03,
          101603.0,
          101406.32,
          101328.02,
          101458.51,
          101335.01,
          101168.18,
          101073.0,
          100984.64,
          100904.85,
          100869.72
        ]
      ],
      "mae": 0.2211
    },
    {
      "target": "light",
      "X": [
        "19:00",
        "20:00",
        "21:00",
        "22:00",
        "23:00",
        "00:00",
        "01:00",
        "02:00",
        "03:00",
        "04:00",
        "05:00",
        "06:00",
        "07:00",
        "08:00",
        "09:00",
        "10:00",
        "11:00",
        "12:00",
        "13:00",
        "14:00",
        "15:00",
        "16:00",
        "17:00",
        "18:00"
      ],
      "y": [
        [
          4743.92,
          3226.02,
          2728.85,
          3537.33,
          2041.62,
          2376.64,
          3541.95,
          -2061.63,
          -1479.28,
          385.43,
          885.26,
          2885.71,
          5722.88,
          6525.13,
          5877.96,
          9941.24,
          13218.55,
          16675.52,
          21971.31,
          26847.92,
          27527.8,
          25587.82,
          22808.92,
          16249.97
        ]
      ],
      "mae": 0.5554
    },
    {
      "target": "Uv",
      "X": [
        "19:00",
        "20:00",
        "21:00",
        "22:00",
        "23:00",
        "00:00",
        "01:00",
        "02:00",
        "03:00",
        "04:00",
        "05:00",
        "06:00",
        "07:00",
        "08:00",
        "09:00",
        "10:00",
        "11:00",
        "12:00",
        "13:00",
        "14:00",
        "15:00",
        "16:00",
        "17:00",
        "18:00"
      ],
      "y": [
        [
          1.1,
          1.3,
          0.82,
          0.2,
          0.18,
          0.36,
          0.3,
          0.03,
          -0.32,
          0.03,
          0.36,
          -0.01,
          0.16,
          0.03,
          0.37,
          0.07,
          0.29,
          0.31,
          0.4,
          0.55,
          0.77,
          1.05,
          1.2,
          1.41
        ]
      ],
      "mae": 0.5135
    }
  ],
  [
    {
      "target": "Temp",
      "X": [
        "19:00",
        "20:00",
        "21:00",
        "22:00",
        "23:00",
        "00:00",
        "01:00",
        "02:00",
        "03:00",
        "04:00",
        "05:00",
        "06:00",
        "07:00",
        "08:00",
        "09:00",
        "10:00",
        "11:00",
        "12:00",
        "13:00",
        "14:00",
        "15:00",
        "16:00",
        "17:00",
        "18:00"
      ],
      "y": [
        [
          21.35,
          21.2,
          19.96,
          17.37,
          17.01,
          16.24,
          16.02,
          15.86,
          15.52,
          15.35,
          15.21,
          14.91,
          16.02,
          15.98,
          16.4,
          16.42,
          17.12,
          16.92,
          17.41,
          17.06,
          17.1,
          18.43,
          18.58,
          18.51
        ]
      ],
      "mae": 0.4117
    },
    {
      "target": "Hum",
      "X": [
        "19:00",
        "20:00",
        "21:00",
        "22:00",
        "23:00",
        "00:00",
        "01:00",
        "02:00",
        "03:00",
        "04:00",
        "05:00",
        "06:00",
        "07:00",
        "08:00",
        "09:00",
        "10:00",
        "11:00",
        "12:00",
        "13:00",
        "14:00",
        "15:00",
        "16:00",
        "17:00",
        "18:00"
      ],
      "y": [
        [
          52.35,
          52.7,
          53.91,
          46.39,
          48.07,
          47.73,
          49.84,
          55.88,
          58.18,
          59.05,
          55.84,
          55.71,
          56.67,
          54.68,
          52.98,
          51.13,
          48.91,
          50.59,
          46.45,
          51.13,
          46.26,
          50.25,
          47.76,
          47.11
        ]
      ],
      "mae": 0.4431
    },
    {
      "target": "pres",
      "X": [
        "19:00",
        "20:00",
        "21:00",
        "22:00",
        "23:00",
        "00:00",
        "01:00",
        "02:00",
        "03:00",
        "04:00",
        "05:00",
        "06:00",
        "07:00",
        "08:00",
        "09:00",
        "10:00",
        "11:00",
        "12:00",
        "13:00",
        "14:00",
        "15:00",
        "16:00",
        "17:00",
        "18:00"
      ],
      "y": [
        [
          101506.74,
          101568.69,
          101601.43,
          101871.2,
          101881.63,
          101770.26,
          101781.13,
          101762.93,
          101653.06,
          101646.5,
          101652.64,
          101637.48,
          101510.34,
          101422.14,
          101384.92,
          101278.22,
          101365.74,
          101122.39,
          101159.91,
          100950.31,
          101109.32,
          100940.04,
          100823.24,
          100870.13
        ]
      ],
      "mae": 0.2686
    },
    {
      "target": "light",
      "X": [
        "19:00",
        "20:00",
        "21:00",
        "22:00",
        "23:00",
        "00:00",
        "01:00",
        "02:00",
        "03:00",
        "04:00",
        "05:00",
        "06:00",
        "07:00",
        "08:00",
        "09:00",
        "10:00",
        "11:00",
        "12:00",
        "13:00",
        "14:00",
        "15:00",
        "16:00",
        "17:00",
        "18:00"
      ],
      "y": [
        [
          5166.4,
          4081.82,
          3740.63,
          1968.17,
          3143.36,
          1176.93,
          158.06,
          1289.83,
          408.31,
          853.52,
          857.92,
          2607.56,
          3382.17,
          4299.19,
          5739.26,
          6398.46,
          10113.79,
          11363.76,
          14934.7,
          17705.19,
          17568.16,
          18554.18,
          17345.71,
          11493.88
        ]
      ],
      "mae": 0.5293
    },
    {
      "target": "Uv",
      "X": [
        "19:00",
        "20:00",
        "21:00",
        "22:00",
        "23:00",
        "00:00",
        "01:00",
        "02:00",
        "03:00",
        "04:00",
        "05:00",
        "06:00",
        "07:00",
        "08:00",
        "09:00",
        "10:00",
        "11:00",
        "12:00",
        "13:00",
        "14:00",
        "15:00",
        "16:00",
        "17:00",
        "18:00"
      ],
      "y": [
        [
          0.77,
          1.0,
          0.74,
          0.22,
          0.18,
          0.31,
          0.24,
          0.18,
          0.11,
          0.16,
          0.24,
          0.15,
          0.28,
          0.36,
          0.55,
          0.33,
          0.36,
          0.43,
          0.3,
          0.4,
          0.2,
          0.32,
          0.38,
          0.44
        ]
      ],
      "mae": 0.4489
    }
  ],
  [
    {
      "target": "Temp",
      "X": [
        "19:00",
        "20:00",
        "21:00",
        "22:00",
        "23:00",
        "00:00",
        "01:00",
        "02:00",
        "03:00",
        "04:00",
        "05:00",
        "06:00",
        "07:00",
        "08:00",
        "09:00",
        "10:00",
        "11:00",
        "12:00",
        "13:00",
        "14:00",
        "15:00",
        "16:00",
        "17:00",
        "18:00"
      ],
      "y": [
        [
          21.35,
          20.87,
          20.11,
          17.88,
          17.35,
          16.94,
          16.55,
          16.54,
          16.22,
          15.74,
          15.56,
          15.93,
          15.87,
          15.58,
          16.46,
          16.41,
          17.21,
          17.44,
          17.86,
          17.68,
          18.01,
          18.12,
          18.08,
          17.87
        ]
      ],
      "mae": 0.3583
    },
    {
      "target": "Hum",
      "X": [
        "19:00",
        "20:00",
        "21:00",
        "22:00",
        "23:00",
        "00:00",
        "01:00",
        "02:00",
        "03:00",
        "04:00",
        "05:00",
        "06:00",
        "07:00",
        "08:00",
        "09:00",
        "10:00",
        "11:00",
        "12:00",
        "13:00",
        "14:00",
        "15:00",
        "16:00",
        "17:00",
        "18:00"
      ],
      "y": [
        [
          66.96,
          67.7,
          66.95,
          73.64,
          74.71,
          76.88,
          75.59,
          76.74,
          77.36,
          75.9,
          73.05,
          69.85,
          67.67,
          64.27,
          63.83,
          61.35,
          65.06,
          67.02,
          67.69,
          68.94,
          72.96,
          76.56,
          76.92,
          81.5
        ]
      ],
      "mae": 0.5451
    },
    {
      "target": "pres",
      "X": [
        "19:00",
        "20:00",
        "21:00",
        "22:00",
        "23:00",
        "00:00",
        "01:00",
        "02:00",
        "03:00",
        "04:00",
        "05:00",
        "06:00",
        "07:00",
        "08:00",
        "09:00",
        "10:00",
        "11:00",
        "12:00",
        "13:00",
        "14:00",
        "15:00",
        "16:00",
        "17:00",
        "18:00"
      ],
      "y": [
        [
          101626.23,
          101619.01,
          101676.58,
          102084.16,
          102100.86,
          102020.55,
          102108.48,
          102016.78,
          101996.24,
          101890.03,
          101983.35,
          101874.85,
          101838.39,
          101803.08,
          101742.15,
          101612.73,
          101434.64,
          101478.46,
          101261.29,
          101168.4,
          101108.02,
          101095.3,
          100953.63,
          100980.88
        ]
      ],
      "mae": 0.3174
    },
    {
      "target": "light",
      "X": [
        "19:00",
        "20:00",
        "21:00",
        "22:00",
        "23:00",
        "00:00",
        "01:00",
        "02:00",
        "03:00",
        "04:00",
        "05:00",
        "06:00",
        "07:00",
        "08:00",
        "09:00",
        "10:00",
        "11:00",
        "12:00",
        "13:00",
        "14:00",
        "15:00",
        "16:00",
        "17:00",
        "18:00"
      ],
      "y": [
        [
          4906.65,
          3698.04,
          2787.79,
          230.67,
          432.99,
          670.33,
          -417.25,
          331.69,
          2171.3,
          3157.98,
          413.9,
          3135.12,
          3742.19,
          5879.9,
          5097.83,
          7782.27,
          9709.61,
          12807.62,
          14233.3,
          17473.17,
          20724.7,
          19800.48,
          18934.73,
          12559.3
        ]
      ],
      "mae": 0.5229
    },
    {
      "target": "Uv",
      "X": [
        "19:00",
        "20:00",
        "21:00",
        "22:00",
        "23:00",
        "00:00",
        "01:00",
        "02:00",
        "03:00",
        "04:00",
        "05:00",
        "06:00",
        "07:00",
        "08:00",
        "09:00",
        "10:00",
        "11:00",
        "12:00",
        "13:00",
        "14:00",
        "15:00",
        "16:00",
        "17:00",
        "18:00"
      ],
      "y": [
        [
          0.9,
          1.12,
          0.87,
          0.27,
          0.49,
          0.55,
          0.44,
          0.2,
          0.37,
          0.5,
          0.72,
          0.69,
          0.35,
          0.3,
          0.21,
          0.29,
          0.31,
          0.52,
          0.57,
          0.46,
          0.39,
          0.24,
          0.51,
          0.42
        ]
      ],
      "mae": 0.5926
    }
  ],
  [
    {
      "target": "Temp",
      "X": [
        "19:00",
        "20:00",
        "21:00",
        "22:00",
        "23:00",
        "00:00",
        "01:00",
        "02:00",
        "03:00",
        "04:00",
        "05:00",
        "06:00",
        "07:00",
        "08:00",
        "09:00",
        "10:00",
        "11:00",
        "12:00",
        "13:00",
        "14:00",
        "15:00",
        "16:00",
        "17:00",
        "18:00"
      ],
      "y": [
        [
          20.52,
          20.14,
          19.45,
          16.17,
          16.2,
          16.58,
          17.67,
          17.2,
          17.89,
          19.9,
          19.73,
          20.82,
          20.76,
          21.96,
          21.68,
          22.56,
          22.78,
          22.32,
          21.47,
          20.58,
          20.83,
          19.79,
          19.18,
          18.64
        ]
      ],
      "mae": 0.4239
    },
    {
      "target": "Hum",
      "X": [
        "19:00",
        "20:00",
        "21:00",
        "22:00",
        "23:00",
        "00:00",
        "01:00",
        "02:00",
        "03:00",
        "04:00",
        "05:00",
        "06:00",
        "07:00",
        "08:00",
        "09:00",
        "10:00",
        "11:00",
        "12:00",
        "13:00",
        "14:00",
        "15:00",
        "16:00",
        "17:00",
        "18:00"
      ],
      "y": [
        [
          65.32,
          66.26,
          66.32,
          68.93,
          70.82,
          70.74,
          72.66,
          72.09,
          71.7,
          72.8,
          67.96,
          67.8,
          67.78,
          68.44,
          69.6,
          70.22,
          69.52,
          72.4,
          74.36,
          76.75,
          78.45,
          80.02,
          77.6,
          77.88
        ]
      ],
      "mae": 0.596
    },
    {
      "target": "pres",
      "X": [
        "19:00",
        "20:00",
        "21:00",
        "22:00",
        "23:00",
        "00:00",
        "01:00",
        "02:00",
        "03:00",
        "04:00",
        "05:00",
        "06:00",
        "07:00",
        "08:00",
        "09:00",
        "10:00",
        "11:00",
        "12:00",
        "13:00",
        "14:00",
        "15:00",
        "16:00",
        "17:00",
        "18:00"
      ],
      "y": [
        [
          101576.78,
          101637.47,
          101738.67,
          102102.07,
          101973.01,
          102121.51,
          102060.17,
          102098.81,
          102011.81,
          101892.66,
          101843.68,
          101801.84,
          101662.68,
          101668.22,
          101616.63,
          101502.74,
          101319.12,
          101370.69,
          101209.39,
          101180.68,
          101063.57,
          100945.3,
          100774.01,
          100710.08
        ]
      ],
      "mae": 0.3235
    },
    {
      "target": "light",
      "X": [
        "19:00",
        "20:00",
        "21:00",
        "22:00",
        "23:00",
        "00:00",
        "01:00",
        "02:00",
        "03:00",
        "04:00",
        "05:00",
        "06:00",
        "07:00",
        "08:00",
        "09:00",
        "10:00",
        "11:00",
        "12:00",
        "13:00",
        "14:00",
        "15:00",
        "16:00",
        "17:00",
        "18:00"
      ],
      "y": [
        [
          804.34,
          1509.29,
          1822.96,
          79.41,
          -174.97,
          -900.76,
          -184.65,
          -122.45,
          -422.96,
          -1025.51,
          930.44,
          1216.21,
          2474.57,
          4855.3,
          9174.02,
          16905.89,
          23700.98,
          28596.79,
          30026.19,
          26594.87,
          22534.6,
          14079.46,
          10517.74,
          4965.49
        ]
      ],
      "mae": 0.5556
    },
    {
      "target": "Uv",
      "X": [
        "19:00",
        "20:00",
        "21:00",
        "22:00",
        "23:00",
        "00:00",
        "01:00",
        "02:00",
        "03:00",
        "04:00",
        "05:00",
        "06:00",
        "07:00",
        "08:00",
        "09:00",
        "10:00",
        "11:00",
        "12:00",
        "13:00",
        "14:00",
        "15:00",
        "16:00",
        "17:00",
        "18:00"
      ],
      "y": [
        [
          0.98,
          1.18,
          0.93,
          0.66,
          0.37,
          0.31,
          0.16,
          -0.05,
          0.15,
          0.07,
          0.18,
          0.51,
          0.5,
          0.21,
          0.6,
          0.71,
          0.79,
          0.73,
          0.84,
          1.2,
          1.14,
          1.22,
          1.34,
          1.32
        ]
      ],
      "mae": 0.5124
    }
  ],
  [
    {
      "target": "Temp",
      "X": [
        "19:00",
        "20:00",
        "21:00",
        "22:00",
        "23:00",
        "00:00",
        "01:00",
        "02:00",
        "03:00",
        "04:00",
        "05:00",
        "06:00",
        "07:00",
        "08:00",
        "09:00",
        "10:00",
        "11:00",
        "12:00",
        "13:00",
        "14:00",
        "15:00",
        "16:00",
        "17:00",
        "18:00"
      ],
      "y": [
        [
          21.14,
          20.71,
          20.05,
          17.43,
          17.21,
          16.38,
          16.47,
          15.85,
          15.97,
          16.39,
          16.96,
          16.75,
          17.75,
          18.06,
          18.89,
          18.12,
          18.59,
          19.43,
          19.42,
          19.68,
          19.64,
          19.5,
          19.74,
          19.14
        ]
      ],
      "mae": 0.3467
    },
    {
      "target": "Hum",
      "X": [
        "19:00",
        "20:00",
        "21:00",
        "22:00",
        "23:00",
        "00:00",
        "01:00",
        "02:00",
        "03:00",
        "04:00",
        "05:00",
        "06:00",
        "07:00",
        "08:00",
        "09:00",
        "10:00",
        "11:00",
        "12:00",
        "13:00",
        "14:00",
        "15:00",
        "16:00",
        "17:00",
        "18:00"
      ],
      "y": [
        [
          59.51,
          60.58,
          59.55,
          59.19,
          61.1,
          63.66,
          63.44,
          66.19,
          68.12,
          68.54,
          67.54,
          65.46,
          66.04,
          68.62,
          67.88,
          68.19,
          69.23,
          70.74,
          68.8,
          68.52,
          72.52,
          71.42,
          69.1,
          69.5
        ]
      ],
      "mae": 0.452
    },
    {
      "target": "pres",
      "X": [
        "19:00",
        "20:00",
        "21:00",
        "22:00",
        "23:00",
        "00:00",
        "01:00",
        "02:00",
        "03:00",
        "04:00",
        "05:00",
        "06:00",
        "07:00",
        "08:00",
        "09:00",
        "10:00",
        "11:00",
        "12:00",
        "13:00",
        "14:00",
        "15:00",
        "16:00",
        "17:00",
        "18:00"
      ],
      "y": [
        [
          101653.94,
          101617.54,
          101685.08,
          102010.99,
          102129.44,
          102131.85,
          102120.35,
          102045.15,
          102081.42,
          101895.44,
          101870.84,
          101772.88,
          101526.92,
          101432.29,
          101355.72,
          101339.13,
          101303.78,
          101109.29,
          101184.45,
          101064.98,
          100933.27,
          100977.47,
          100868.84,
          100932.68
        ]
      ],
      "mae": 0.2796
    },
    {
      "target": "light",
      "X": [
        "19:00",
        "20:00",
        "21:00",
        "22:00",
        "23:00",
        "00:00",
        "01:00",
        "02:00",
        "03:00",
        "04:00",
        "05:00",
        "06:00",
        "07:00",
        "08:00",
        "09:00",
        "10:00",
        "11:00",
        "12:00",
        "13:00",
        "14:00",
        "15:00",
        "16:00",
        "17:00",
        "18:00"
      ],
      "y": [
        [
          5018.51,
          4596.47,
          3629.09,
          2500.78,
          855.29,
          2086.81,
          1858.65,
          -621.05,
          3698.31,
          2536.04,
          2332.09,
          4215.84,
          3973.64,
          4144.58,
          5119.5,
          8639.93,
          12177.21,
          13214.6,
          17649.25,
          17344.92,
          16392.29,
          16901.03,
          13039.71,
          12804.77
        ]
      ],
      "mae": 0.5263
    },
    {
      "target": "Uv",
      "X": [
        "19:00",
        "20:00",
        "21:00",
        "22:00",
        "23:00",
        "00:00",
        "01:00",
        "02:00",
        "03:00",
        "04:00",
        "05:00",
        "06:00",
        "07:00",
        "08:00",
        "09:00",
        "10:00",
        "11:00",
        "12:00",
        "13:00",
        "14:00",
        "15:00",
        "16:00",
        "17:00",
        "18:00"
      ],
      "y": [
        [
          0.86,
          0.93,
          0.74,
          0.27,
          0.35,
          0.23,
          0.24,
          0.26,
          0.23,
          0.27,
          0.21,
          0.28,
          0.3,
          0.3,
          0.23,
          0.32,
          0.35,
          0.37,
          0.23,
          0.24,
          0.21,
          0.35,
          0.23,
          0.35
        ]
      ],
      "mae": 0.4584
    }
  ]
]